{"data":{"allSearchKeywordsJson":{"edges":[{"node":{"pid":"Calendar#addCssClass","parentPid":"Calendar","name":"addCssClass"}},{"node":{"pid":"Calendar#changeLanguage","parentPid":"Calendar","name":"changeLanguage"}},{"node":{"pid":"Calendar#destroy","parentPid":"Calendar","name":"destroy"}},{"node":{"pid":"Calendar#draw","parentPid":"Calendar","name":"draw"}},{"node":{"pid":"Calendar#event-draw","parentPid":"Calendar","name":"draw"}},{"node":{"pid":"Calendar#drawNext","parentPid":"Calendar","name":"drawNext"}},{"node":{"pid":"Calendar#drawPrev","parentPid":"Calendar","name":"drawPrev"}},{"node":{"pid":"Calendar#getDate","parentPid":"Calendar","name":"getDate"}},{"node":{"pid":"Calendar#getDateElements","parentPid":"Calendar","name":"getDateElements"}},{"node":{"pid":"Calendar#getNextDate","parentPid":"Calendar","name":"getNextDate"}},{"node":{"pid":"Calendar#getNextYearDate","parentPid":"Calendar","name":"getNextYearDate"}},{"node":{"pid":"Calendar#getPrevDate","parentPid":"Calendar","name":"getPrevDate"}},{"node":{"pid":"Calendar#getPrevYearDate","parentPid":"Calendar","name":"getPrevYearDate"}},{"node":{"pid":"Calendar#getType","parentPid":"Calendar","name":"getType"}},{"node":{"pid":"Calendar#hide","parentPid":"Calendar","name":"hide"}},{"node":{"pid":"Calendar#removeCssClass","parentPid":"Calendar","name":"removeCssClass"}},{"node":{"pid":"Calendar#show","parentPid":"Calendar","name":"show"}},{"node":{"pid":"Calendar","parentPid":"class","name":"Calendar"}},{"node":{"pid":"DatePicker#addCssClass","parentPid":"DatePicker","name":"addCssClass"}},{"node":{"pid":"DatePicker#addOpener","parentPid":"DatePicker","name":"addOpener"}},{"node":{"pid":"DatePicker#addRange","parentPid":"DatePicker","name":"addRange"}},{"node":{"pid":"DatePicker#event-change","parentPid":"DatePicker","name":"change"}},{"node":{"pid":"DatePicker#changeLanguage","parentPid":"DatePicker","name":"changeLanguage"}},{"node":{"pid":"DatePicker#event-close","parentPid":"DatePicker","name":"close"}},{"node":{"pid":"DatePicker#close","parentPid":"DatePicker","name":"close"}},{"node":{"pid":"DatePicker#createCalendar","parentPid":"DatePicker","name":"createCalendar"}},{"node":{"pid":"DatePicker#createRangePicker","parentPid":"DatePicker","name":"createRangePicker"}},{"node":{"pid":"DatePicker#destroy","parentPid":"DatePicker","name":"destroy"}},{"node":{"pid":"DatePicker#disable","parentPid":"DatePicker","name":"disable"}},{"node":{"pid":"DatePicker#event-draw","parentPid":"DatePicker","name":"draw"}},{"node":{"pid":"DatePicker#drawLowerCalendar","parentPid":"DatePicker","name":"drawLowerCalendar"}},{"node":{"pid":"DatePicker#drawUpperCalendar","parentPid":"DatePicker","name":"drawUpperCalendar"}},{"node":{"pid":"DatePicker#enable","parentPid":"DatePicker","name":"enable"}},{"node":{"pid":"DatePicker#findOverlappedRange","parentPid":"DatePicker","name":"findOverlappedRange"}},{"node":{"pid":"DatePicker#getCalendar","parentPid":"DatePicker","name":"getCalendar"}},{"node":{"pid":"DatePicker#getCalendarType","parentPid":"DatePicker","name":"getCalendarType"}},{"node":{"pid":"DatePicker#getDate","parentPid":"DatePicker","name":"getDate"}},{"node":{"pid":"DatePicker#getDateElements","parentPid":"DatePicker","name":"getDateElements"}},{"node":{"pid":"DatePicker#getLocaleText","parentPid":"DatePicker","name":"getLocaleText"}},{"node":{"pid":"DatePicker#getTimePicker","parentPid":"DatePicker","name":"getTimePicker"}},{"node":{"pid":"DatePicker#getType","parentPid":"DatePicker","name":"getType"}},{"node":{"pid":"DatePicker#isDisabled","parentPid":"DatePicker","name":"isDisabled"}},{"node":{"pid":"DatePicker#isOpened","parentPid":"DatePicker","name":"isOpened"}},{"node":{"pid":"DatePicker#isSelectable","parentPid":"DatePicker","name":"isSelectable"}},{"node":{"pid":"DatePicker#isSelected","parentPid":"DatePicker","name":"isSelected"}},{"node":{"pid":"DatePicker#localeTexts","parentPid":"DatePicker","name":"localeTexts"}},{"node":{"pid":"DatePicker#event-open","parentPid":"DatePicker","name":"open"}},{"node":{"pid":"DatePicker#open","parentPid":"DatePicker","name":"open"}},{"node":{"pid":"DatePicker#removeAllOpeners","parentPid":"DatePicker","name":"removeAllOpeners"}},{"node":{"pid":"DatePicker#removeCssClass","parentPid":"DatePicker","name":"removeCssClass"}},{"node":{"pid":"DatePicker#removeOpener","parentPid":"DatePicker","name":"removeOpener"}},{"node":{"pid":"DatePicker#removeRange","parentPid":"DatePicker","name":"removeRange"}},{"node":{"pid":"DatePicker#setDate","parentPid":"DatePicker","name":"setDate"}},{"node":{"pid":"DatePicker#setDateFormat","parentPid":"DatePicker","name":"setDateFormat"}},{"node":{"pid":"DatePicker#setInput","parentPid":"DatePicker","name":"setInput"}},{"node":{"pid":"DatePicker#setNull","parentPid":"DatePicker","name":"setNull"}},{"node":{"pid":"DatePicker#setRanges","parentPid":"DatePicker","name":"setRanges"}},{"node":{"pid":"DatePicker#setType","parentPid":"DatePicker","name":"setType"}},{"node":{"pid":"DatePicker#toggle","parentPid":"DatePicker","name":"toggle"}},{"node":{"pid":"DatePicker","parentPid":"class","name":"DatePicker"}},{"node":{"pid":"DateRangePicker#addRange","parentPid":"DateRangePicker","name":"addRange"}},{"node":{"pid":"DateRangePicker#event-change:end","parentPid":"DateRangePicker","name":"change:end"}},{"node":{"pid":"DateRangePicker#event-change:start","parentPid":"DateRangePicker","name":"change:start"}},{"node":{"pid":"DateRangePicker#changeLanguage","parentPid":"DateRangePicker","name":"changeLanguage"}},{"node":{"pid":"DateRangePicker#destroy","parentPid":"DateRangePicker","name":"destroy"}},{"node":{"pid":"DateRangePicker#getEndDate","parentPid":"DateRangePicker","name":"getEndDate"}},{"node":{"pid":"DateRangePicker#getEndpicker","parentPid":"DateRangePicker","name":"getEndpicker"}},{"node":{"pid":"DateRangePicker#getStartDate","parentPid":"DateRangePicker","name":"getStartDate"}},{"node":{"pid":"DateRangePicker#getStartpicker","parentPid":"DateRangePicker","name":"getStartpicker"}},{"node":{"pid":"DateRangePicker#removeRange","parentPid":"DateRangePicker","name":"removeRange"}},{"node":{"pid":"DateRangePicker#setEndDate","parentPid":"DateRangePicker","name":"setEndDate"}},{"node":{"pid":"DateRangePicker#setRanges","parentPid":"DateRangePicker","name":"setRanges"}},{"node":{"pid":"DateRangePicker#setStartDate","parentPid":"DateRangePicker","name":"setStartDate"}},{"node":{"pid":"DateRangePicker","parentPid":"class","name":"DateRangePicker"}},{"node":{"pid":"tutorial-example01-basic","parentPid":"example","name":"1. Basic"}},{"node":{"pid":"tutorial-example02-inline-style","parentPid":"example","name":"2. Inline style"}},{"node":{"pid":"tutorial-example03-selectable-ranges","parentPid":"example","name":"3. Having selectable ranges"}},{"node":{"pid":"tutorial-example04-having-timepicker","parentPid":"example","name":"4. Having Timepicker"}},{"node":{"pid":"tutorial-example05-picking-month","parentPid":"example","name":"5. Picking month"}},{"node":{"pid":"tutorial-example06-picking-year","parentPid":"example","name":"6. Picking year"}},{"node":{"pid":"tutorial-example07-calendar","parentPid":"example","name":"7. Calendar"}},{"node":{"pid":"tutorial-example08-daterangepicker","parentPid":"example","name":"8. DateRangePicker"}},{"node":{"pid":"tutorial-example09-changing-type","parentPid":"example","name":"9. Changing type"}}]}}}